{"content": {"suites": {"0": {"status": {"total_pass": 1, "total_skip": 0, "total_xpass": 0, "total_xfail": 0, "total_rerun": 0, "total_fail": 5, "total_error": 0}, "tests": {"0": {"status": "PASS", "message": "", "test_name": "test_naver_login", "rerun": "0"}, "1": {"status": "FAIL", "message": "       playwright._impl._errors.TimeoutError: Page.wait_for_selector: Timeout 3000ms exceeded.\n       Call log:\n       waiting for locator(\"text=\uba54\uc77c\uc774 \uc800\uc7a5\ub418\uc5c8\uc2b5\ub2c8\ub2e4\") to be visible\n           Failed: Test failed: Page.wait_for_selector: Timeout 3000ms exceeded.\n           Call log:\n           waiting for locator(\"text=\uba54\uc77c\uc774 \uc800\uc7a5\ub418\uc5c8\uc2b5\ub2c8\ub2e4\") to be visible\n", "test_name": "test_naver_normal_send", "rerun": "0"}, "2": {"status": "FAIL", "message": "       playwright._impl._errors.TimeoutError: Page.wait_for_selector: Timeout 3000ms exceeded.\n       Call log:\n       waiting for locator(\"text=\uad00\ub9ac\uc790\uc5d0 \uc758\ud574 \ucc28\ub2e8\ub418\uc5c8\uc2b5\ub2c8\ub2e4. \uad00\ub9ac\uc790\uc5d0 \ubb38\uc758 \ud558\uc138\uc694\") to be visible\n           Failed: Test failed: Page.wait_for_selector: Timeout 3000ms exceeded.\n           Call log:\n           waiting for locator(\"text=\uad00\ub9ac\uc790\uc5d0 \uc758\ud574 \ucc28\ub2e8\ub418\uc5c8\uc2b5\ub2c8\ub2e4. \uad00\ub9ac\uc790\uc5d0 \ubb38\uc758 \ud558\uc138\uc694\") to be visible\n", "test_name": "test_naver_pattern_send", "rerun": "0"}, "3": {"status": "FAIL", "message": "       playwright._impl._errors.TimeoutError: Page.wait_for_selector: Timeout 3000ms exceeded.\n       Call log:\n       waiting for locator(\"text=\uad00\ub9ac\uc790\uc5d0 \uc758\ud574 \ucc28\ub2e8\ub418\uc5c8\uc2b5\ub2c8\ub2e4. \uad00\ub9ac\uc790\uc5d0 \ubb38\uc758 \ud558\uc138\uc694\") to be visible\n           Failed: Test failed: Page.wait_for_selector: Timeout 3000ms exceeded.\n           Call log:\n           waiting for locator(\"text=\uad00\ub9ac\uc790\uc5d0 \uc758\ud574 \ucc28\ub2e8\ub418\uc5c8\uc2b5\ub2c8\ub2e4. \uad00\ub9ac\uc790\uc5d0 \ubb38\uc758 \ud558\uc138\uc694\") to be visible\n", "test_name": "test_naver_keyword_send", "rerun": "0"}, "4": {"status": "FAIL", "message": "       playwright._impl._errors.TimeoutError: Page.wait_for_selector: Timeout 3000ms exceeded.\n       Call log:\n       waiting for locator(\"text=\uad00\ub9ac\uc790\uc5d0 \uc758\ud574 \ucc28\ub2e8\ub418\uc5c8\uc2b5\ub2c8\ub2e4. \uad00\ub9ac\uc790\uc5d0 \ubb38\uc758 \ud558\uc138\uc694\") to be visible\n           Failed: Test failed: Page.wait_for_selector: Timeout 3000ms exceeded.\n           Call log:\n           waiting for locator(\"text=\uad00\ub9ac\uc790\uc5d0 \uc758\ud574 \ucc28\ub2e8\ub418\uc5c8\uc2b5\ub2c8\ub2e4. \uad00\ub9ac\uc790\uc5d0 \ubb38\uc758 \ud558\uc138\uc694\") to be visible\n", "test_name": "test_naver_attach_send", "rerun": "0"}, "5": {"status": "FAIL", "message": "       playwright._impl._errors.Error: Page.goto: net::ERR_CERT_AUTHORITY_INVALID at https://172.16.150.185:8443/login\n       Call log:\n       navigating to \"https://172.16.150.185:8443/login\", waiting until \"load\"\n", "test_name": "test_compare_result_naver_mail", "rerun": "0"}}, "suite_name": "test_services/mail/naver_mail/test_naver_mail_compare.py"}}}, "date": "November 25, 2024", "start_time": 1732502226.1761124, "total_suite": 1, "status": "FAIL", "status_list": {"pass": "1", "fail": "5", "skip": "0", "error": "0", "xpass": "0", "xfail": "0", "rerun": "0"}, "total_tests": "6"}